alertbox/__init__.py
alertbox/alertbox.py
alertbox-0.0.3.dist-info/LICENSE.txt
alertbox-0.0.3.dist-info/METADATA
alertbox-0.0.3.dist-info/WHEEL
alertbox-0.0.3.dist-info/top_level.txt
alertbox-0.0.3.dist-info/RECORD
