Metadata-Version: 2.1
Name: alertbox
Version: 0.0.3
Summary: Simple MessageBox Builder
Home-page: https://github.com/HajMasterX/alertbox
Author: HajMasterX
Author-email: masterxq22@gmail.com
License-File: LICENSE.txt
